outerr2html/README.MD
outerr2html/__init__.py
outerr2html/requirements.txt
outerr2html/thirdparty.json
outerr2html-0.11.dist-info/LICENSE.rst
outerr2html-0.11.dist-info/METADATA
outerr2html-0.11.dist-info/WHEEL
outerr2html-0.11.dist-info/top_level.txt
outerr2html-0.11.dist-info/RECORD
