Metadata-Version: 2.1
Name: outerr2html
Version: 0.11
Summary: Pipe stdout/stderr to TXT/HTML (Windows only)
Home-page: https://github.com/hansalemaos/outerr2html
Author: Johannes Fischer
Author-email: aulasparticularesdealemaosp@gmail.com
License: MIT
Keywords: requests,ip,v4
Classifier: Development Status :: 4 - Beta
Classifier: Programming Language :: Python :: 3 :: Only
Classifier: Programming Language :: Python :: 3.10
Classifier: Topic :: Software Development :: Libraries :: Python Modules
Classifier: Topic :: Utilities
License-File: LICENSE.rst
Requires-Dist: aiofiles
Requires-Dist: tkkillablethreads
